LICENSE
MANIFEST.in
README.rst
requirements.txt
setup.cfg
setup.py
django_organice.egg-info/PKG-INFO
django_organice.egg-info/SOURCES.txt
django_organice.egg-info/dependency_links.txt
django_organice.egg-info/entry_points.txt
django_organice.egg-info/not-zip-safe
django_organice.egg-info/requires.txt
django_organice.egg-info/top_level.txt
docs/Makefile
docs/alternatives.rst
docs/changelog.rst
docs/components.rst
docs/conf.py
docs/configuration.rst
docs/contributing.rst
docs/index.rst
docs/installation.rst
docs/overview.rst
docs/requirements.txt
docs/themes.rst
docs/locale/de/LC_MESSAGES/alternatives.mo
docs/locale/de/LC_MESSAGES/alternatives.po
docs/locale/de/LC_MESSAGES/changelog.mo
docs/locale/de/LC_MESSAGES/changelog.po
docs/locale/de/LC_MESSAGES/components.mo
docs/locale/de/LC_MESSAGES/components.po
docs/locale/de/LC_MESSAGES/configuration.mo
docs/locale/de/LC_MESSAGES/configuration.po
docs/locale/de/LC_MESSAGES/contributing.mo
docs/locale/de/LC_MESSAGES/contributing.po
docs/locale/de/LC_MESSAGES/index.mo
docs/locale/de/LC_MESSAGES/index.po
docs/locale/de/LC_MESSAGES/installation.mo
docs/locale/de/LC_MESSAGES/installation.po
docs/locale/de/LC_MESSAGES/overview.mo
docs/locale/de/LC_MESSAGES/overview.po
docs/locale/de/LC_MESSAGES/themes.mo
docs/locale/de/LC_MESSAGES/themes.po
docs/locale/it/LC_MESSAGES/alternatives.mo
docs/locale/it/LC_MESSAGES/alternatives.po
docs/locale/it/LC_MESSAGES/changelog.mo
docs/locale/it/LC_MESSAGES/changelog.po
docs/locale/it/LC_MESSAGES/components.mo
docs/locale/it/LC_MESSAGES/components.po
docs/locale/it/LC_MESSAGES/configuration.mo
docs/locale/it/LC_MESSAGES/configuration.po
docs/locale/it/LC_MESSAGES/contributing.mo
docs/locale/it/LC_MESSAGES/contributing.po
docs/locale/it/LC_MESSAGES/index.mo
docs/locale/it/LC_MESSAGES/index.po
docs/locale/it/LC_MESSAGES/installation.mo
docs/locale/it/LC_MESSAGES/installation.po
docs/locale/it/LC_MESSAGES/overview.mo
docs/locale/it/LC_MESSAGES/overview.po
docs/locale/it/LC_MESSAGES/themes.mo
docs/locale/it/LC_MESSAGES/themes.po
organice/__init__.py
organice/context_processors.py
organice/models.py
organice/settings.py
organice/urls.py
organice/auth/__init__.py
organice/auth/adapters.py
organice/auth/groups.py
organice/auth/permissions.py
organice/bin/__init__.py
