Metadata-Version: 1.1
Name: django-organice
Version: 0.4.0
Summary: All-in-one collaboration solution providing an intuitive, consistent user experience.
Home-page: https://organice.io/
Author: Peter Bittner
Author-email: django@bittner.it
License: Apache 2.0
Keywords: cms,collaboration,blog,newsletter,django,python
Platform: UNKNOWN
Classifier: Development Status :: 3 - Alpha
Classifier: Environment :: Web Environment
Classifier: Framework :: Django
Classifier: Intended Audience :: Developers
Classifier: License :: OSI Approved :: Apache Software License
Classifier: Operating System :: OS Independent
Classifier: Programming Language :: Python
Classifier: Programming Language :: Python :: 2
Classifier: Programming Language :: Python :: 2.7
Classifier: Programming Language :: Python :: 3
Classifier: Programming Language :: Python :: 3.3
Classifier: Programming Language :: Python :: 3.4
Classifier: Topic :: Office/Business :: Groupware
